{
  "rain": "GOTO spring",
  "Sun": "MAIL FSJulianaShort/GOTO SunSleep/GOTO SunFun",
  "SunFun": "0 Lizzie.Stoffton_Boarding 26 7/610 Lizzie.Stoffton_Boarding 24 20 2/800 Lizzie.Stoffton_Yoba 28 17 0/1210 Lizzie.Stoffton_Boarding 30 8 2/2200 Lizzie.Stoffton_Boarding 26 7 Juliana_sleep",
  "SunSleep": "0 Lizzie.Stoffton_Boarding 26 7/610 Lizzie.Stoffton_Boarding 26 7 \"Strings\\schedules\\JulianaFS:Sunday.000\"/1200 Lizzie.Stoffton_Cafe 2 18 2/1430 Lizzie.Stoffton_Boarding 31 23 1 \"Strings\\schedules\\JulianaFS:Sunday.001\"/2200 Lizzie.Stoffton_Boarding 26 7 Juliana_sleep",
  "spring": "MAIL FSJulianaShort/GOTO LongHours/GOTO ShortHours",
  //arrives 8:30
  "LongHours": "0 Lizzie.Stoffton_Boarding 26 7/610 Lizzie.Stoffton_Boarding 24 20 2/640 Lizzie.Stoffton_Mill 20 23 0/850 Lizzie.Stoffton_Mill 15 23 0/910 Lizzie.Stoffton_Mill 15 25 2/930 Lizzie.Stoffton_Mill 20 25 2/950 Lizzie.Stoffton_Mill 20 23 0/1010 Lizzie.Stoffton_Mill 25 23 0/1030 Lizzie.Stoffton_Mill 25 25 2/1100 Lizzie.Stoffton_Mill 29 25 Juliana_rest/1200 Lizzie.Stoffton_Mill 25 23 0/1220 Lizzie.Stoffton_Mill 25 25 2/1240 Lizzie.Stoffton_Mill 20 25 2/1300 Lizzie.Stoffton_Mill 20 23 0/1320 Lizzie.Stoffton_Mill 15 23 0/1340 Lizzie.Stoffton_Mill 15 25 2/1400 Lizzie.Stoffton_Mill 20 25 2/1420 Lizzie.Stoffton_Mill 20 23 0/1440 Lizzie.Stoffton_Mill 25 23 0/1600 Lizzie.Stoffton_Mill 25 25 2/1620 Lizzie.Stoffton_Mill 20 25 2/1640 Lizzie.Stoffton_Mill 20 23 0/1700 Lizzie.Stoffton_Mill 29 25 Juliana_rest/1730 Lizzie.Stoffton_Mill 15 23 0/1750 Lizzie.Stoffton_Mill 15 25 2/1810 Lizzie.Stoffton_Mill 20 25 2/1830 Lizzie.Stoffton_Mill 20 23 0/1850 Lizzie.Stoffton_Mill 25 23 0/1910 Lizzie.Stoffton_Mill 25 25 2/1930 Lizzie.Stoffton_Mill 20 23 0/2000 Lizzie.Stoffton_Boarding 30 8 2/2200 Lizzie.Stoffton_Boarding 26 7 Juliana_sleep",
  "ShortHours": "0 Lizzie.Stoffton_Boarding 26 7/610 Lizzie.Stoffton_Boarding 24 20 2/640 Lizzie.Stoffton_Mill 20 23 0/850 Lizzie.Stoffton_Mill 15 23 0/910 Lizzie.Stoffton_Mill 15 25 2/930 Lizzie.Stoffton_Mill 20 25 2/950 Lizzie.Stoffton_Mill 20 23 0/1010 Lizzie.Stoffton_Mill 25 23 0/1030 Lizzie.Stoffton_Mill 25 25 2/1100 Lizzie.Stoffton_Mill 8 11 0/1200 Lizzie.Stoffton_Mill 25 23 0/1220 Lizzie.Stoffton_Mill 25 25 2/1240 Lizzie.Stoffton_Mill 20 25 2/1300 Lizzie.Stoffton_Mill 20 23 0/1320 Lizzie.Stoffton_Mill 15 23 0/1340 Lizzie.Stoffton_Mill 15 25 2/1400 Lizzie.Stoffton_Mill 20 25 2/1420 Lizzie.Stoffton_Mill 20 23 0/1440 Lizzie.Stoffton_Mill 25 23 0/1600 Lizzie.Stoffton_Mill 25 25 2/1620 Lizzie.Stoffton_Mill 20 25 2/1640 Lizzie.Stoffton_Mill 20 23 0/1700 Lizzie.Stoffton_Boarding 30 8 2/2200 Lizzie.Stoffton_Boarding 26 7 Juliana_sleep",
}