{
  "Changes": [

	{	
		"Action": "EditData",
		"Target": "Characters/Dialogue/Mike",
		"Entries": {
  "Introduction": "{{i18n: Intro.Mike}}",
  "danceRejection": "{{i18n: DanceRejection.Mike}}",
  "divorced": "{{i18n: Divorced.Mike}}",
  "breakUp": "{{i18n: BreakUp.Mike}}",
  "dumped_Guys": "{{i18n: Dumped.Mike}}",
  "secondChance_Guys": "{{i18n: Chance.Mike}}",
  "Mon": "{{i18n: MonJust.Mike}}",
  "Mon2": "{{i18n: Mon2.Mike}}",
  "Mon4": "{{i18n: Mon4.Mike}}",
  "Mon6": "{{i18n: Mon6.Mike}}",
  "Mon8": "{{i18n: Mon8.Mike}}",
  "Mon10": "{{i18n: Mon10.Mike}}",
  "Tue": "{{i18n: TueJust.MikeJasper}}",
  "Tue2": "{{i18n: Tue2.Mike}}",
  "Tue4": "{{i18n: Tue4.Mike}}",
  "Tue6": "{{i18n: Tue6.Mike}}",
  "Tue8": "{{i18n: Tue8.Mike}}",
  "Tue10": "{{i18n: Tue10.Mike}}",
  "Wed": "{{i18n: WedJust.MikeJasper}}",
  "Wed2": "{{i18n: Wed2.Mike}}",
  "Wed4": "{{i18n: Wed4.Mike}}",
  "Wed6": "{{i18n: Wed6.Mike}}",
  "Wed8": "{{i18n: Wed8.Mike}}",
  "Wed10": "{{i18n: Wed10.Mike}}",
  "Thu": "{{i18n: ThuJust.Mike}}",
  "Thu2": "{{i18n: Thu2.Mike}}",
  "Thu4": "{{i18n: Thu4.Mike}}",
  "Thu6": "{{i18n: Thu6.Mike}}",
  "Thu8": "{{i18n: Thu8.Mike}}",
  "Thu10": "{{i18n: Thu10.Mike}}",
  "Fri": "{{i18n: FriJust.Mike}}",
  "Fri2": "{{i18n: Fri2.Mike}}",
  "Fri4": "{{i18n: Fri4.Mike}}",
  "Fri6": "{{i18n: Fri6.Mike}}",
  "Fri8": "{{i18n: Fri8.Mike}}",
  "Fri10": "{{i18n: Fri10.Mike}}",
  "Sat": "{{i18n: SatJust.Mike}}",
  "Sat2": "{{i18n: Sat2.Mike}}",
  "Sat4": "{{i18n: Sat4.Mike}}",
  "Sat6": "{{i18n: Sat6.Mike}}",
  "Sat8": "{{i18n: Sat8.Mike}}",
  "Sat10": "{{i18n: Sat10.Mike}}",
  "Sun": "{{i18n: SunnJust.Mike}}",
  "Sun2": "{{i18n: Sun2.Mike}}",
  "Sun4": "{{i18n: Sun4.Mike}}",
  "Sun6": "{{i18n: Sun6.Mike}}",
  "Sun8": "{{i18n: Sun8.Mike}}",
  "Sun10": "{{i18n: Sun10.Mike}}",
  "spring_Wed": "{{i18n: SpringWed.Mike}}",
  "spring_Sat": "{{i18n: SpringSat.Mike}}",
  "summer_Mon": "{{i18n: SummerMon.Mike}}",
  "summer_Tue": "{{i18n: SummerTue.Mike}}",
  "summer_Wed": "{{i18n: SummerWed.Mike}}",
  "summer_Thu": "{{i18n: SummerThu.Mike}}",
  "summer_Fri": "{{i18n: SummerFri.Mike}}",
  "summer_Sat": "{{i18n: SummerSat.Mike}}",
  "summer_Sun": "{{i18n: SummerSun.Mike}}",
  "summer_12": "{{i18n: Summer12.Mike}}",
  "Sat10_2": "{{i18n: Sat10.Mike2}}",
  "fall_Fri": "{{i18n: FallFri.Mike}}",
  "fall_Sat": "{{i18n: FallSat.Mike}}",
  "Sun10_4": "{{i18n: Sun10.Mike4}}",
  "winter_Wed": "{{i18n: WinterWed.Mike}}",
  "winter_Sun": "{{i18n: WinterSun.Mike}}",
  "give_flowersA": "{{i18n: FlowerA.Mike}}",
  "give_flowersB": "{{i18n: FlowerB.Mike}}",
  "give_pendant": "{{i18n: Pendant.Mike}}",
  "stardrop_gift": "{{i18n: StarDrop.Mike}}",
  "reject_two_heartA": "{{i18n: Reject2A.Mike}}",
  "reject_two_heartB": "{{i18n: Reject2B.Mike}}",
  "reject_four_heartA": "{{i18n: Reject4A.Mike}}",
  "reject_four_heartB": "{{i18n: Reject4B.Mike}}",
  "engageA": "{{i18n: EngageA.Mike}}",
  "engageB": "{{i18n: EngageB.Mike}}",
  "marriedA": "{{i18n: MarriedA.Mike}}",
  "marriedB": "{{i18n: MarriedB.Mike}}",
  "refusal_no_heartsA": "{{i18n: RefuseNoA.Mike}}",
  "refusal_no_heartsB": "{{i18n: RefuseNoB.Mike}}",
  "refusal_knownA": "{{i18n: RefuseKnowA.Mike}}",
  "refusal_knownB": "{{i18n: RefuseKnowB.Mike}}",
  "refusal_botherA": "{{i18n: RefuseBotherA.Mike}}",
  "refusal_botherB": "{{i18n: RefuseBotherB.Mike}}",
  "spring_12": "{{i18n: Spring12.Mike}}",
  "spring_23": "{{i18n: Spring23.Mike}}",
  "summer_10": "{{i18n: Summer10.Mike}}",
  "summer_28": "{{i18n: Summer28.Mike}}",
  "fall_15": "{{i18n: Fall15.Mike}}",
  "fall_27": "{{i18n: Fall27.Mike}}",  
  "winter_7": "{{i18n: Winter7.Mike}}",
  "winter_24": "{{i18n: Winter24.Mike}}",
  "Resort_Entering": "{{i18n: EnterResort.Mike}}",
  "Resort_Leaving": "{{i18n: LeavingResort.Mike}}",
  "Resort_Shore": "{{i18n: ShoreResort.Mike}}",
  "Resort_Umbrella": "{{i18n: UmbrellaResort.Mike}}",
  "Resort_Wander": "{{i18n: WanderResort.Mike}}",
  "Resort_Bar": "{{i18n: BarResort.Mike}}",
  "Resort": "{{i18n: JustResort.Mike}}",
		}
	},

]
}