{
  "SingleOverrides": {
    "VoidEel": {
      "PondColor": {
        "R": 120,
        "G": 20,
        "B": 110
      },
      "FishID": "FlashShifter.StardewValleyExpandedCP_Void_Eel"
    },
    "RadioactiveBass": {
      "PondColor": {
        "R": 124,
        "G": 252,
        "B": 0
      },
      "FishID": "FlashShifter.StardewValleyExpandedCP_Radioactive_Bass"
    },
    "Butterfish": {
      "PondColor": {
        "R": 255,
        "G": 255,
        "B": 153
      },
      "FishID": "FlashShifter.StardewValleyExpandedCP_Butterfish"
    }
  },
  "GroupOverrides": {}
}