{
    "Changes": [

      // CATEGORY OVERRIDE 

  // ANCIENT AMARANTH 
  {
    "Action": "EditData",
    "Target": "Data/Objects",
    "Entries": {
      "{{ModID}}_ancientamaranth": {
        "Name": "Ancient Amaranth",
        "DisplayName": "{{i18n: crop.ancientamaranth.name}}",
        "Description": "{{i18n: crop.ancientamaranth.description}}",
        "Type": "Vegetable",
        "Category": -75,
        "Price": 160,
        "Edibility": 50,
        "IsDrink": false,
        "ExcludeFromShippingCollection": "{{ExcludeFromPerfection}}",
        "Texture": "{{InternalAssetKey: assets/Items & Crops/SnSObjects.png}}",
        "SpriteIndex": 0,
        "ContextTags": [ "color_cyan", "category_vegetable", "seedmaker_banned" ],
      }
    }
  },

  {
    "Action": "EditData",
    "Target": "Data/Objects",
    "Entries": {
      "{{ModID}}_ancientamaranth.seed": {
        "Name": "Ancient Amaranth Seeds",
        "DisplayName": "{{i18n: crop.ancientamaranth.seed.name}}",
        "Description": "{{i18n: crop.ancientamaranth.seed.description}}",
        "Type": "Seeds",
        "Category": -74,
        "Price": 2,
        "IsDrink": false,
        "ExcludeFromShippingCollection": "{{ExcludeFromPerfection}}",
        "Texture": "{{InternalAssetKey: assets/Items & Crops/SnSObjects.png}}",
        "SpriteIndex": 9
      }
    }
  },

  {
    "Action": "EditData",
    "Target": "Data/Crops",
    "Entries": {
      "{{ModID}}_ancientamaranth.seed": {
        "Seasons": [ "summer", "fall" ],
        "DaysInPhase": [ 1, 2, 2, 2 ],
        "HarvestItemId": "{{ModID}}_ancientamaranth",
        "HarvestMethod": "Scythe",
        "HarvestMinStack": 1,
        "HarvestMaxStack": 2,
        "ExtraHarvestChance": 0.03,
        "ExcludeFromShippingCollection": "{{ExcludeFromPerfection}}",
        "Texture": "{{InternalAssetKey: assets/Items & Crops/SnSCrops.png}}",
        "SpriteIndex": 0
      }
    }
  },

   // ANCIENT EPIPHYTIC FERN 
   {
    "Action": "EditData",
    "Target": "Data/Objects",
    "Entries": {
      "{{ModID}}_ancientepiphyticfern": {
        "Name": "Ancient Epiphytic Fern",
        "DisplayName": "{{i18n: crop.ancientepiphyticfern.name}}",
        "Description": "{{i18n: crop.ancientepiphyticfern.description}}",
        "Type": "Vegetable",
        "Category": -75,
        "Price": 300,
        "Edibility": 50,
        "ExcludeFromShippingCollection": "{{ExcludeFromPerfection}}",
        "IsDrink": false,
        "Texture": "{{InternalAssetKey: assets/Items & Crops/SnSObjects.png}}",
        "SpriteIndex": 2,
        "ContextTags": [ "color_cyan", "category_vegetable", "seedmaker_banned" ],
      }
    }
  },

  {
    "Action": "EditData",
    "Target": "Data/Objects",
    "Entries": {
      "{{ModID}}_ancientepiphyticfern.seed": {
        "Name": "Ancient Amaranth Seeds",
        "DisplayName": "{{i18n: crop.ancientepiphyticfern.seed.name}}",
        "Description": "{{i18n: crop.ancientepiphyticfern.seed.description}}",
        "Type": "Seeds",
        "Category": -74,
        "Price": 2,
        "ExcludeFromShippingCollection": "{{ExcludeFromPerfection}}",
        "IsDrink": false,
        "Texture": "{{InternalAssetKey: assets/Items & Crops/SnSObjects.png}}",
        "SpriteIndex": 11
      }
    }
  },

  {
    "Action": "EditData",
    "Target": "Data/Crops",
    "Entries": {
      "{{ModID}}_ancientepiphyticfern.seed": {
        "Seasons": [ "spring", "summer" ],
        "DaysInPhase": [ 1, 3, 3, 4, 3 ],
        "RegrowDays": 3,
        "HarvestItemId": "{{ModID}}_ancientepiphyticfern",
        "HarvestMethod": "Scythe",
        "HarvestMinStack": 1,
        "HarvestMaxStack": 1,
        "ExcludeFromShippingCollection": "{{ExcludeFromPerfection}}",
        "ExtraHarvestChance": 0.03,
        "Texture": "{{InternalAssetKey: assets/Items & Crops/SnSCrops.png}}",
        
        "SpriteIndex": 2
      }
    }
  },

     // ANCIENT GLOWING POLYPORE MUSHROOM
     {
      "Action": "EditData",
      "Target": "Data/Objects",
      "Entries": {
        "{{ModID}}_glowingpolyporemushrooms": {
          "Name": "Ancient Glowing Polypore Mushroom",
          "DisplayName": "{{i18n: crop.ancientglowingpolyporemushrooms.name}}",
          "Description": "{{i18n: crop.ancientglowingpolyporemushrooms.description}}",
          "Type": "Vegetable",
          "Category": -75,
          "Price": 300,
          "Edibility": 50,
          "ExcludeFromShippingCollection": "{{ExcludeFromPerfection}}",
          "IsDrink": false,
          "Texture": "{{InternalAssetKey: assets/Items & Crops/SnSObjects.png}}",
          "SpriteIndex": 4,
          "ContextTags": [ "color_cyan", "category_vegetable", "seedmaker_banned" ],
        }
      }
    },
  
    {
      "Action": "EditData",
      "Target": "Data/Objects",
      "Entries": {
        "{{ModID}}_glowingpolyporemushrooms.seed": {
          "Name": "Ancient Glowing Polypore Mushroom Spores",
          "DisplayName": "{{i18n: crop.ancientglowingpolyporemushrooms.seed.name}}",
          "Description": "{{i18n: crop.ancientglowingpolyporemushrooms.seed.description}}",
          "Type": "Seeds",
          "Category": -74,
          "ExcludeFromShippingCollection": "{{ExcludeFromPerfection}}",
          "Price": 2,
          "IsDrink": false,
          "Texture": "{{InternalAssetKey: assets/Items & Crops/SnSObjects.png}}",
          "SpriteIndex": 13
        }
      }
    },
  
    {
      "Action": "EditData",
      "Target": "Data/Crops",
      "Entries": {
        "{{ModID}}_glowingpolyporemushrooms.seed": {
          "Seasons": [ "fall", "winter" ],
          "DaysInPhase": [ 2, 7, 7, 7, 5 ],
          "RegrowDays": 3,
          "HarvestItemId": "{{ModID}}_glowingpolyporemushrooms",
          "HarvestMinStack": 1,
          "HarvestMaxStack": 1,
          "ExcludeFromShippingCollection": "{{ExcludeFromPerfection}}",
          "Texture": "{{InternalAssetKey: assets/Items & Crops/SnSCrops.png}}",
          "SpriteIndex": 4
        }
      }
    },

     // ANCIENT WILD FAIRY ROSE
     {
      "Action": "EditData",
      "Target": "Data/Objects",
      "Entries": {
        "{{ModID}}_ancientwildfairyrose": {
          "Name": "Ancient Wild Fairy Rose",
          "DisplayName": "{{i18n: crop.ancientwildfairyrose.name}}",
          "Description": "{{i18n: crop.ancientwildfairyrose.description}}",
          "Type": "Flower",
          "Category": -80,
          "Price": 345,
          "Edibility": 50,
          "IsDrink": false,
          "ExcludeFromShippingCollection": "{{ExcludeFromPerfection}}",
          "Texture": "{{InternalAssetKey: assets/Items & Crops/SnSObjects.png}}",
          "SpriteIndex": 1,
          "ContextTags": [ "color_cyan", "category_flowers", "seedmaker_banned" ],
        }
      }
    },
  
    {
      "Action": "EditData",
      "Target": "Data/Objects",
      "Entries": {
        "{{ModID}}_ancientwildfairyrose.seed": {
          "Name": "Ancient Wild Fairy Rose Seeds",
          "DisplayName": "{{i18n: crop.ancientwildfairyrose.seed.name}}",
          "Description": "{{i18n: crop.ancientwildfairyrose.seed.description}}",
          "Type": "Seeds",
          "Category": -74,
          "Price": 2,
          "IsDrink": false,
          "ExcludeFromShippingCollection": "{{ExcludeFromPerfection}}",
          "Texture": "{{InternalAssetKey: assets/Items & Crops/SnSObjects.png}}",
          "SpriteIndex": 10
        }
      }
    },
  
    {
      "Action": "EditData",
      "Target": "Data/Crops",
      "Entries": {
        "{{ModID}}_ancientwildfairyrose.seed": {
          "Seasons": [ "spring", "summer", "fall" ],
          "DaysInPhase": [ 2, 7, 7, 7, 5 ],
          "RegrowDays": 3,
          "HarvestItemId": "{{ModID}}_ancientwildfairyrose",
          "HarvestMinStack": 1,
          "HarvestMaxStack": 3,
          "ExcludeFromShippingCollection": "{{ExcludeFromPerfection}}",
          "Texture": "{{InternalAssetKey: assets/Items & Crops/SnSCrops.png}}",
          "SpriteIndex": 6
        }
      }
    },

   // ANCIENT ELDERBERRY
   {
    "Action": "EditData",
    "Target": "Data/Objects",
    "Entries": {
      "{{ModID}}_ancientelderberry": {
        "Name": "Ancient Elderberry",
        "DisplayName": "{{i18n: crop.ancientelderberry.name}}",
        "Description": "{{i18n: crop.ancientelderberry.description}}",
        "Type": "Fruit",
        "Category": -79,
        "Price": 110,
        "Edibility": 50,
        "IsDrink": false,
        "ExcludeFromShippingCollection": "{{ExcludeFromPerfection}}",
        "Texture": "{{InternalAssetKey: assets/Items & Crops/SnSObjects.png}}",
        "SpriteIndex": 37,
        "ContextTags": [ "color_cyan", "category_fruits", "seedmaker_banned" ],
      }
    }
  },

  {
    "Action": "EditData",
    "Target": "Data/Objects",
    "Entries": {
      "{{ModID}}_ancientelderberry.seed": {
        "Name": "Ancient Elderberry Seeds",
        "DisplayName": "{{i18n: crop.ancientelderberry.seed.name}}",
        "Description": "{{i18n: crop.ancientelderberry.seed.description}}",
        "Type": "Seeds",
        "Category": -74,
        "Price": 2,
        "ExcludeFromShippingCollection": "{{ExcludeFromPerfection}}",
        "IsDrink": false,
        "Texture": "{{InternalAssetKey: assets/Items & Crops/SnSObjects.png}}",
        "SpriteIndex": 38
      }
    }
  },

  {
    "Action": "EditData",
    "Target": "Data/Crops",
    "Entries": {
      "{{ModID}}_ancientelderberry.seed": {
        "Seasons": [ "spring", "summer" ],
        "DaysInPhase": [ 1, 1, 1, 3, 4 ],
        "RegrowDays": 3,
        "HarvestItemId": "{{ModID}}_ancientelderberry",
        "HarvestMinStack": 1,
        "HarvestMaxStack": 3,
        "ExtraHarvestChance": 0.03,
        "ExcludeFromShippingCollection": "{{ExcludeFromPerfection}}",
        "Texture": "{{InternalAssetKey: assets/Items & Crops/SnSCrops.png}}",
        "SpriteIndex": 8
      }
    }
  },

   // ANCIENT BOTTLE GOURD
   {
    "Action": "EditData",
    "Target": "Data/Objects",
    "Entries": {
      "{{ModID}}_ancientbottlegourd": {
        "Name": "Ancient Bottle Gourd",
        "DisplayName": "{{i18n: crop.ancientbottlegourd.name}}",
        "Description": "{{i18n: crop.ancientbottlegourd.description}}",
        "Type": "Vegetable",
        "Category": -75,
        "Price": 220,
        "Edibility": 50,
        "IsDrink": false,
        "Texture": "{{InternalAssetKey: assets/Items & Crops/SnSObjects.png}}",
        "SpriteIndex": 39,
        "ExcludeFromShippingCollection": "{{ExcludeFromPerfection}}",
        "ContextTags": [ "color_cyan", "category_fruits", "seedmaker_banned" ],
      }
    }
  },

  {
    "Action": "EditData",
    "Target": "Data/Objects",
    "Entries": {
      "{{ModID}}_ancientbottlegourd.seed": {
        "Name": "Ancient Bottle Gourd",
        "DisplayName": "{{i18n: crop.ancientbottlegourd.seed.name}}",
        "Description": "{{i18n: crop.ancientbottlegourd.seed.description}}",
        "Type": "Seeds",
        "Category": -74,
        "Price": 2,
        "IsDrink": false,
        "ExcludeFromShippingCollection": "{{ExcludeFromPerfection}}",
        "Texture": "{{InternalAssetKey: assets/Items & Crops/SnSObjects.png}}",
        "SpriteIndex": 40
      }
    }
  },

  {
    "Action": "EditData",
    "Target": "Data/Crops",
    "Entries": {
      "{{ModID}}_ancientbottlegourd.seed": {
        "Seasons": [ "fall" ],
        "DaysInPhase": [ 1, 2, 2, 2, 3, 2],
        "HarvestItemId": "{{ModID}}_ancientbottlegourd",
        "HarvestMinStack": 1,
        "HarvestMaxStack": 2,
        "ExtraHarvestChance": 0.03,
        "ExcludeFromShippingCollection": "{{ExcludeFromPerfection}}",
        "Texture": "{{InternalAssetKey: assets/Items & Crops/SnSCrops.png}}",
        "SpriteIndex": 10
      }
    }
  },

   // ANCIENT GIANT APPLE BERRY
   {
    "Action": "EditData",
    "Target": "Data/Objects",
    "Entries": {
      "{{ModID}}_ancientgiantappleberry": {
        "Name": "Ancient Giant Apple Berry",
        "DisplayName": "{{i18n: crop.ancientgiantappleberry.name}}",
        "Description": "{{i18n: crop.ancientgiantappleberry.description}}",
        "Type": "Fruit",
        "Category": -79,
        "Price": 275,
        "Edibility": 50,
        "IsDrink": false,
        "ExcludeFromShippingCollection": "{{ExcludeFromPerfection}}",
        "Texture": "{{InternalAssetKey: assets/Items & Crops/SnSObjects.png}}",
        "SpriteIndex": 41,
        "ContextTags": [ "color_cyan", "category_fruits", "seedmaker_banned" ],
      }
    }
  },

  {
    "Action": "EditData",
    "Target": "Data/Objects",
    "Entries": {
      "{{ModID}}_ancientgiantappleberry.seed": {
        "Name": "Ancient Giant Apple Berry",
        "DisplayName": "{{i18n: crop.ancientgiantappleberry.seed.name}}",
        "Description": "{{i18n: crop.ancientgiantappleberry.seed.description}}",
        "Type": "Seeds",
        "Category": -74,
        "Price": 2,
        "ExcludeFromShippingCollection": "{{ExcludeFromPerfection}}",
        "IsDrink": false,
        "Texture": "{{InternalAssetKey: assets/Items & Crops/SnSObjects.png}}",
        "SpriteIndex": 42
      }
    }
  },

  {
    "Action": "EditData",
    "Target": "Data/Crops",
    "Entries": {
      "{{ModID}}_ancientgiantappleberry.seed": {
        "Seasons": [ "spring", "summer", "fall" ],
        "DaysInPhase": [ 1, 2, 3, 4],
        "HarvestItemId": "{{ModID}}_ancientgiantappleberry",
        "HarvestMinStack": 1,
        "HarvestMaxStack": 2,
        "ExtraHarvestChance": 0.03,
        "ExcludeFromShippingCollection": "{{ExcludeFromPerfection}}",
        "Texture": "{{InternalAssetKey: assets/Items & Crops/SnSCrops.png}}",
        "SpriteIndex": 12
      }
    }
  },

     // ANCIENT AZURE DETURA FLOWER
     {
      "Action": "EditData",
      "Target": "Data/Objects",
      "Entries": {
        "{{ModID}}_ancientazuredetura": {
          "Name": "Ancient Azure Detura Flower",
          "DisplayName": "{{i18n: crop.ancientazuredetura.name}}",
          "Description": "{{i18n: crop.ancientazuredetura.description}}",
          "Type": "Flower",
          "Category": -80,
          "Price": 160,
          "Edibility": 50,
          "IsDrink": false,
          "ExcludeFromShippingCollection": "{{ExcludeFromPerfection}}",
          "Texture": "{{InternalAssetKey: assets/Items & Crops/SnSObjects.png}}",
          "SpriteIndex": 43,
          "ContextTags": [ "color_cyan", "category_flowers", "seedmaker_banned" ],
        }
      }
    },
  
    {
      "Action": "EditData",
      "Target": "Data/Objects",
      "Entries": {
        "{{ModID}}_ancientazuredetura.seed": {
          "Name": "Ancient Azure Detura Flower",
          "DisplayName": "{{i18n: crop.ancientazuredetura.seed.name}}",
          "Description": "{{i18n: crop.ancientazuredetura.seed.description}}",
          "Type": "Seeds",
          "Category": -74,
          "Price": 2,
          "ExcludeFromShippingCollection": "{{ExcludeFromPerfection}}",
          "IsDrink": false,
          "Texture": "{{InternalAssetKey: assets/Items & Crops/SnSObjects.png}}",
          "SpriteIndex": 44
        }
      }
    },
  
    {
      "Action": "EditData",
      "Target": "Data/Crops",
      "Entries": {
        "{{ModID}}_ancientazuredetura.seed": {
          "Seasons": [ "fall", "winter" ],
          "DaysInPhase": [ 1, 2, 3, 2],
          "HarvestItemId": "{{ModID}}_ancientazuredetura",
          "HarvestMinStack": 1,
          "HarvestMaxStack": 2,
          "ExcludeFromShippingCollection": "{{ExcludeFromPerfection}}",
          "Texture": "{{InternalAssetKey: assets/Items & Crops/SnSCrops.png}}",
          "SpriteIndex": 14
        }
      }
    },
    
      // ANCIENT GLOWING HUCKLEBERRY VINE
      {
        "Action": "EditData",
        "Target": "Data/Objects",
        "Entries": {
          "{{ModID}}_ancientglowinghuckleberry": {
            "Name": "Ancient Glowing Huckleberry",
            "DisplayName": "{{i18n: crop.ancientglowinghuckleberry.name}}",
            "Description": "{{i18n: crop.ancientglowinghuckleberry.description}}",
            "Type": "Fruit",
            "Category": -79,
            "Price": 410,
            "Edibility": 50,
            "ExcludeFromShippingCollection": "{{ExcludeFromPerfection}}",
            "IsDrink": false,
            "Texture": "{{InternalAssetKey: assets/Items & Crops/SnSObjects.png}}",
            "SpriteIndex": 3,
            "ContextTags": [ "color_cyan", "category_fruits", "seedmaker_banned" ],
          }
        }
      },
    
      {
        "Action": "EditData",
        "Target": "Data/Objects",
        "Entries": {
          "{{ModID}}_ancientglowinghuckleberry.seed": {
            "Name": "Ancient Glowing Huckleberry Seeds",
            "DisplayName": "{{i18n: crop.ancientglowinghuckleberry.seed.name}}",
            "Description": "{{i18n: crop.ancientglowinghuckleberry.seed.description}}",
            "Type": "Seeds",
            "Category": -74,
            "Price": 2,
            "IsDrink": false,
            "ExcludeFromShippingCollection": "{{ExcludeFromPerfection}}",
            "Texture": "{{InternalAssetKey: assets/Items & Crops/SnSObjects.png}}",
            "SpriteIndex": 12
          }
        }
      },
    
      {
        "Action": "EditData",
        "Target": "Data/fruitTrees",
        "Entries": {
          "{{ModID}}_ancientglowinghuckleberry.seed": {
            "Seasons": [ "summer" ],
            "Fruit": [ { "Id": "N/A", "ItemId": "{{ModID}}_ancientglowinghuckleberry" } ],
            "Texture": "{{InternalAssetKey: assets/Items & Crops/SnSTrees.png}}",
            "ExcludeFromShippingCollection": "{{ExcludeFromPerfection}}",
            "SpriteIndex": 0
            
          }
        }
      },

      // CRAFTING RECIPES 
      {
      "Action": "EditData",
      "Target": "Data/CraftingRecipes",
      "Entries":
      {
      "Ancient Amaranth Seeds": "{{ModID}}_druidicessence 4/what is this for?/{{ModID}}_ancientamaranth.seed 1/false/null/{{i18n:AncientSeed.Hector.Amaranth}}",

      "Ancient Epiphytic Fern Seeds": "{{ModID}}_druidicessence 6/what is this for?/{{ModID}}_ancientepiphyticfern.seed 1/false/null/{{i18n:AncientSeed.Hector.Fern}}",

      "Ancient Glowing Huckleberry Seeds": "{{ModID}}_druidicessence 8/what is this for?/{{ModID}}_ancientglowinghuckleberry.seed 1/false/null/{{i18n:AncientSeed.Hector.Huckleberry}}",

      "Ancient Glowing Polypore Mushroom Spores": "{{ModID}}_druidicessence 6/what is this for?/{{ModID}}_glowingpolyporemushrooms.seed 1/false/null/{{i18n:AncientSeed.Hector.Mushroom}}",

      "Ancient Wild Fairy Rose Seeds": "{{ModID}}_druidicessence 5/what is this for?/{{ModID}}_ancientwildfairyrose.seed 1/false/null/{{i18n:AncientSeed.Hector.FairyRose}}",

      "Ancient Elderberry Seeds": "{{ModID}}_druidicessence 6/what is this for?/{{ModID}}_ancientelderberry.seed 1/false/null/{{i18n:AncientSeed.Hector.Elderberry}}",

      "Ancient Bottle Gourd Seeds": "{{ModID}}_druidicessence 4/what is this for?/{{ModID}}_ancientbottlegourd.seed 1/false/null/{{i18n:AncientSeed.Hector.BottleGourd}}",

      "Ancient Giant Apple Berry Seeds": "{{ModID}}_druidicessence 6/what is this for?/{{ModID}}_ancientgiantappleberry.seed 1/false/null/{{i18n:AncientSeed.Hector.AppleBerry}}",

      "Ancient Azure Detura": "{{ModID}}_druidicessence 4/what is this for?/{{ModID}}_ancientazuredetura.seed 1/false/null/{{i18n:AncientSeed.Hector.Detura}}",
      
      }
    },

    // CUSTOM DRUIDIC CATEGORY 

    {
      "Action": "EditData",
      "Target": "spacechase0.SpaceCore/ObjectExtensionData",
      "Entries": {
        "{{ModID}}_ancientamaranth": {
          "CategoryTextOverride": "Druidic",
          "CategoryColorOverride": {
            "R": 48,
            "G": 162,
            "B": 218,
            "A": 255
          },
        },
        "{{ModID}}_ancientepiphyticfern": {
          "CategoryTextOverride": "Druidic",
          "CategoryColorOverride": {
            "R": 48,
            "G": 162,
            "B": 218,
            "A": 255
          },
        },
        "{{ModID}}_glowingpolyporemushrooms": {
          "CategoryTextOverride": "Druidic",
          "CategoryColorOverride": {
            "R": 48,
            "G": 162,
            "B": 218,
            "A": 255
          },
        },
        "{{ModID}}_ancientwildfairyrose": {
          "CategoryTextOverride": "Druidic",
          "CategoryColorOverride": {
            "R": 48,
            "G": 162,
            "B": 218,
            "A": 255
          },
        },
        "{{ModID}}_ancientglowinghuckleberry": {
          "CategoryTextOverride": "Druidic",
          "CategoryColorOverride": {
            "R": 48,
            "G": 162,
            "B": 218,
            "A": 255
          },
        },
        "{{ModID}}_ancientamaranth.seed": {
          "CategoryTextOverride": "Druidic",
          "CategoryColorOverride": {
            "R": 48,
            "G": 162,
            "B": 218,
            "A": 255
          },
        },
        "{{ModID}}_ancientepiphyticfern.seed": {
          "CategoryTextOverride": "Druidic",
          "CategoryColorOverride": {
            "R": 48,
            "G": 162,
            "B": 218,
            "A": 255
          },
        },
        "{{ModID}}_glowingpolyporemushrooms.seed": {
          "CategoryTextOverride": "Druidic",
          "CategoryColorOverride": {
            "R": 48,
            "G": 162,
            "B": 218,
            "A": 255
          },
        },
        "{{ModID}}_ancientwildfairyrose.seed": {
          "CategoryTextOverride": "Druidic",
          "CategoryColorOverride": {
            "R": 48,
            "G": 162,
            "B": 218,
            "A": 255
          },
        },
        "{{ModID}}_ancientglowinghuckleberry.seed": {
          "CategoryTextOverride": "Druidic",
          "CategoryColorOverride": {
            "R": 48,
            "G": 162,
            "B": 218,
            "A": 255
          },
        },
        "{{ModID}}_ancientelderberry": {
          "CategoryTextOverride": "Druidic",
          "CategoryColorOverride": {
            "R": 48,
            "G": 162,
            "B": 218,
            "A": 255
          },
        },
        "{{ModID}}_ancientelderberry.seed": {
          "CategoryTextOverride": "Druidic",
          "CategoryColorOverride": {
            "R": 48,
            "G": 162,
            "B": 218,
            "A": 255
          },
        },
        "{{ModID}}_ancientbottlegourd": {
          "CategoryTextOverride": "Druidic",
          "CategoryColorOverride": {
            "R": 48,
            "G": 162,
            "B": 218,
            "A": 255
          },
        },
        "{{ModID}}_ancientbottlegourd.seed": {
          "CategoryTextOverride": "Druidic",
          "CategoryColorOverride": {
            "R": 48,
            "G": 162,
            "B": 218,
            "A": 255
          },
        },
        "{{ModID}}_ancientgiantappleberry": {
          "CategoryTextOverride": "Druidic",
          "CategoryColorOverride": {
            "R": 48,
            "G": 162,
            "B": 218,
            "A": 255
          },
        },
        "{{ModID}}_ancientgiantappleberry.seed": {
          "CategoryTextOverride": "Druidic",
          "CategoryColorOverride": {
            "R": 48,
            "G": 162,
            "B": 218,
            "A": 255
          },
        },
        "{{ModID}}_ancientazuredetura": {
          "CategoryTextOverride": "Druidic",
          "CategoryColorOverride": {
            "R": 48,
            "G": 162,
            "B": 218,
            "A": 255
          },
        },
        "{{ModID}}_ancientazuredetura.seed": {
          "CategoryTextOverride": "Druidic",
          "CategoryColorOverride": {
            "R": 48,
            "G": 162,
            "B": 218,
            "A": 255
          },
        },
      }
    },
  
        
    ]
}